README.md
setup.py
beerhawk_behavioural_clusters/__init__.py
beerhawk_behavioural_clusters/algo.py
beerhawk_behavioural_clusters/readData.py
beerhawk_behavioural_clusters.egg-info/PKG-INFO
beerhawk_behavioural_clusters.egg-info/SOURCES.txt
beerhawk_behavioural_clusters.egg-info/dependency_links.txt
beerhawk_behavioural_clusters.egg-info/not-zip-safe
beerhawk_behavioural_clusters.egg-info/top_level.txt