Metadata-Version: 2.1
Name: beerhawk-behavioural-clusters
Version: 0.0.13
Summary: Gaussian distributions
Home-page: UNKNOWN
Author: Shashi Bhushan Singh
Author-email: shashi.bhushansingh@ab-inbev.com
License: UNKNOWN
Platform: UNKNOWN
